taskhawk/__init__.py
taskhawk/commands.py
taskhawk/consumer.py
taskhawk/exceptions.py
taskhawk/heartbeat.py
taskhawk/instrumentation.py
taskhawk/models.py
taskhawk/publisher.py
taskhawk/py.typed
taskhawk/task_manager.py
taskhawk/backends/__init__.py
taskhawk/backends/aws.py
taskhawk/backends/base.py
taskhawk/backends/exceptions.py
taskhawk/backends/gcp.py
taskhawk/backends/import_utils.py
taskhawk/backends/utils.py
taskhawk/conf/__init__.py
taskhawk-4.7.0.dist-info/LICENSE.md
taskhawk-4.7.0.dist-info/METADATA
taskhawk-4.7.0.dist-info/WHEEL
taskhawk-4.7.0.dist-info/top_level.txt
taskhawk-4.7.0.dist-info/RECORD
