Metadata-Version: 2.1
Name: taskhawk
Version: 4.7.0
Summary: Taskhawk Python Library
Home-page: https://github.com/cloudchacho/taskhawk-python
Author: Automatic Labs
Maintainer: Aniruddha Maru
Maintainer-email: aniruddhamaru@gmail.com
License: Apache Software License (Apache License 2.0)
Keywords: python taskhawk
Platform: UNKNOWN
Classifier: Natural Language :: English
Classifier: Development Status :: 5 - Production/Stable
Classifier: Intended Audience :: Developers
Classifier: Intended Audience :: System Administrators
Classifier: Topic :: Software Development :: Libraries :: Python Modules
Classifier: Programming Language :: Python
Classifier: Programming Language :: Python :: 3.6
Classifier: Programming Language :: Python :: 3.7
Classifier: License :: OSI Approved :: Apache Software License
Requires-Python: >=3.6
License-File: LICENSE.md
Requires-Dist: funcy
Requires-Dist: arrow
Requires-Dist: dataclasses; python_version < "3.7"
Provides-Extra: aws
Requires-Dist: boto3; extra == "aws"
Requires-Dist: retrying; extra == "aws"
Provides-Extra: dev
Requires-Dist: flake8; extra == "dev"
Requires-Dist: pip-tools; extra == "dev"
Requires-Dist: wheel; extra == "dev"
Requires-Dist: boto3-stubs[sns,sqs]; extra == "dev"
Requires-Dist: types-dataclasses; extra == "dev"
Requires-Dist: docutils<0.18; python_version < "3.8" and extra == "dev"
Requires-Dist: Sphinx==3.2.1; python_version < "3.8" and extra == "dev"
Requires-Dist: jinja2<3.1; (python_version >= "3.7" and python_version < "3.8") and extra == "dev"
Requires-Dist: build==0.10.0; (python_version >= "3.7" and python_version < "3.8") and extra == "dev"
Requires-Dist: Sphinx>3; python_version >= "3.8" and extra == "dev"
Provides-Extra: gcp
Requires-Dist: google-cloud-pubsub>=2.0.0; extra == "gcp"
Requires-Dist: grpcio-status==1.48.2; extra == "gcp"
Provides-Extra: opentelemetry
Requires-Dist: opentelemetry-api<=1.12; python_version < "3.8" and extra == "opentelemetry"
Requires-Dist: opentelemetry-api>=1.19; python_version >= "3.8" and extra == "opentelemetry"
Provides-Extra: publish
Requires-Dist: bumpversion; extra == "publish"
Requires-Dist: twine; extra == "publish"
Provides-Extra: test
Requires-Dist: black; extra == "test"
Requires-Dist: coverage; extra == "test"
Requires-Dist: coveralls; extra == "test"
Requires-Dist: flake8; extra == "test"
Requires-Dist: ipdb; extra == "test"
Requires-Dist: moto<5; extra == "test"
Requires-Dist: mypy; extra == "test"
Requires-Dist: pytest; extra == "test"
Requires-Dist: pytest-cov; extra == "test"
Requires-Dist: pytest-env; extra == "test"
Requires-Dist: opentelemetry-sdk<=1.12; python_version < "3.8" and extra == "test"
Requires-Dist: opentelemetry-sdk>=1.19; python_version >= "3.8" and extra == "test"
